pulsarbat/__init__.py
pulsarbat/core.py
pulsarbat/fft.py
pulsarbat/utils.py
pulsarbat/contrib/__init__.py
pulsarbat/contrib/misc.py
pulsarbat/pulsar/__init__.py
pulsarbat/pulsar/phase.py
pulsarbat/pulsar/predictor.py
pulsarbat/readers/__init__.py
pulsarbat/readers/_base.py
pulsarbat/readers/_baseband_readers.py
pulsarbat/transforms/__init__.py
pulsarbat/transforms/dedispersion.py
pulsarbat/transforms/transforms.py
tests/__init__.py
tests/test_baseband_readers.py
tests/test_contrib.py
tests/test_dedispersion.py
tests/test_fft.py
tests/test_phase_predictor.py
tests/test_polarization.py
tests/test_radio_signal.py
tests/test_readers.py
tests/test_signal.py
tests/test_transforms.py
tests/test_utils.py
tests/data/fake.0.raw
tests/data/fake.1.raw
tests/data/fake.2.raw
tests/data/fake.3.raw
tests/data/sample.dada
tests/data/sample.vdif
tests/data/stokes_ef.dada
tests/data/timing.dat
pulsarbat-0.0.9.dist-info/LICENSE
pulsarbat-0.0.9.dist-info/METADATA
pulsarbat-0.0.9.dist-info/WHEEL
pulsarbat-0.0.9.dist-info/top_level.txt
pulsarbat-0.0.9.dist-info/RECORD
