Metadata-Version: 2.1
Name: pulsarbat
Version: 0.0.9
Summary: pulsarbat (PULSAR Baseband Analysis Tools) is a Python package for analysis of radio baseband observations of pulsars.
Home-page: https://github.com/theXYZT/pulsarbat
Author: Nikhil Mahajan
Author-email: mahajan@astro.utoronto.ca
License: GNU General Public License v3
Keywords: science,astronomy,astrophysics,pulsars,radio,signal
Classifier: Intended Audience :: Science/Research
Classifier: Topic :: Scientific/Engineering :: Astronomy
Classifier: Operating System :: OS Independent
Classifier: License :: OSI Approved :: GNU General Public License v3 (GPLv3)
Classifier: Natural Language :: English
Classifier: Programming Language :: Python
Classifier: Programming Language :: Python :: 3
Classifier: Programming Language :: Python :: 3.9
Classifier: Programming Language :: Python :: 3.10
Classifier: Programming Language :: Python :: 3.11
Requires-Python: >=3.9
License-File: LICENSE
Requires-Dist: astropy (>=5.2)
Requires-Dist: numpy (>=1.23)
Requires-Dist: scipy (>=1.10)
Requires-Dist: baseband (>=4.1.1)
Requires-Dist: dask[array] (>=2023.2.1)
